{
  "description": "Read EIA-608 Closed Caption codes from input video and write them to frame metadata.",
  "input_types": [
    {
      "name": "default",
      "type": "video"
    }
  ],
  "is_dynamic_inputs": false,
  "is_dynamic_outputs": false,
  "is_slice_threading_supported": true,
  "is_support_framesync": false,
  "is_support_timeline": true,
  "name": "readeia608",
  "options": [
    {
      "alias": [
        "scan_min"
      ],
      "choices": [],
      "default": 0,
      "description": "set from which line to scan for codes (from 0 to INT_MAX) (default 0)",
      "flags": "..FV.....T.",
      "max": "INT_MAX",
      "min": "0",
      "name": "scan_min",
      "typing": "int"
    },
    {
      "alias": [
        "scan_max"
      ],
      "choices": [],
      "default": 29,
      "description": "set to which line to scan for codes (from 0 to INT_MAX) (default 29)",
      "flags": "..FV.....T.",
      "max": "INT_MAX",
      "min": "0",
      "name": "scan_max",
      "typing": "int"
    },
    {
      "alias": [
        "spw"
      ],
      "choices": [],
      "default": 0.27,
      "description": "set ratio of width reserved for sync code detection (from 0.1 to 0.7) (default 0.27)",
      "flags": "..FV.....T.",
      "max": "0.7",
      "min": "0.1",
      "name": "spw",
      "typing": "float"
    },
    {
      "alias": [
        "chp"
      ],
      "choices": [],
      "default": 0,
      "description": "check and apply parity bit (default false)",
      "flags": "..FV.....T.",
      "max": null,
      "min": null,
      "name": "chp",
      "typing": "boolean"
    },
    {
      "alias": [
        "lp"
      ],
      "choices": [],
      "default": 1,
      "description": "lowpass line prior to processing (default true)",
      "flags": "..FV.....T.",
      "max": null,
      "min": null,
      "name": "lp",
      "typing": "boolean"
    }
  ],
  "output_types": [
    {
      "name": "default",
      "type": "video"
    }
  ]
}
