{
  "description": "Boost or alter saturation.",
  "input_types": [
    {
      "name": "default",
      "type": "video"
    }
  ],
  "is_dynamic_inputs": false,
  "is_dynamic_outputs": false,
  "is_slice_threading_supported": true,
  "is_support_framesync": false,
  "is_support_timeline": true,
  "name": "vibrance",
  "options": [
    {
      "alias": [
        "intensity"
      ],
      "choices": [],
      "default": 0.0,
      "description": "set the intensity value (from -2 to 2) (default 0)",
      "flags": "..FV.....T.",
      "max": "2",
      "min": "-2",
      "name": "intensity",
      "typing": "float"
    },
    {
      "alias": [
        "rbal"
      ],
      "choices": [],
      "default": 1.0,
      "description": "set the red balance value (from -10 to 10) (default 1)",
      "flags": "..FV.....T.",
      "max": "10",
      "min": "-10",
      "name": "rbal",
      "typing": "float"
    },
    {
      "alias": [
        "gbal"
      ],
      "choices": [],
      "default": 1.0,
      "description": "set the green balance value (from -10 to 10) (default 1)",
      "flags": "..FV.....T.",
      "max": "10",
      "min": "-10",
      "name": "gbal",
      "typing": "float"
    },
    {
      "alias": [
        "bbal"
      ],
      "choices": [],
      "default": 1.0,
      "description": "set the blue balance value (from -10 to 10) (default 1)",
      "flags": "..FV.....T.",
      "max": "10",
      "min": "-10",
      "name": "bbal",
      "typing": "float"
    },
    {
      "alias": [
        "rlum"
      ],
      "choices": [],
      "default": 0.072186,
      "description": "set the red luma coefficient (from 0 to 1) (default 0.072186)",
      "flags": "..FV.....T.",
      "max": "1",
      "min": "0",
      "name": "rlum",
      "typing": "float"
    },
    {
      "alias": [
        "glum"
      ],
      "choices": [],
      "default": 0.715158,
      "description": "set the green luma coefficient (from 0 to 1) (default 0.715158)",
      "flags": "..FV.....T.",
      "max": "1",
      "min": "0",
      "name": "glum",
      "typing": "float"
    },
    {
      "alias": [
        "blum"
      ],
      "choices": [],
      "default": 0.212656,
      "description": "set the blue luma coefficient (from 0 to 1) (default 0.212656)",
      "flags": "..FV.....T.",
      "max": "1",
      "min": "0",
      "name": "blum",
      "typing": "float"
    },
    {
      "alias": [
        "alternate"
      ],
      "choices": [],
      "default": 0,
      "description": "use alternate colors (default false)",
      "flags": "..FV.....T.",
      "max": null,
      "min": null,
      "name": "alternate",
      "typing": "boolean"
    }
  ],
  "output_types": [
    {
      "name": "default",
      "type": "video"
    }
  ]
}
