{
  "description": "Draw text on top of video frames using libfreetype library.",
  "filter_type": "vf",
  "formula_input_typings": null,
  "formula_output_typings": null,
  "id": "ff_vf_drawtext",
  "input_stream_typings": [
    {
      "name": "default",
      "type": "video"
    }
  ],
  "is_input_dynamic": false,
  "is_output_dynamic": false,
  "is_support_framesync": false,
  "is_support_timeline": true,
  "name": "drawtext",
  "options": [
    {
      "alias": [
        "fontfile"
      ],
      "choices": [],
      "default": null,
      "description": "set font file",
      "name": "fontfile",
      "required": false,
      "typing": "String"
    },
    {
      "alias": [
        "text"
      ],
      "choices": [],
      "default": null,
      "description": "set text",
      "name": "text",
      "required": false,
      "typing": "String"
    },
    {
      "alias": [
        "textfile"
      ],
      "choices": [],
      "default": null,
      "description": "set text file",
      "name": "textfile",
      "required": false,
      "typing": "String"
    },
    {
      "alias": [
        "fontcolor"
      ],
      "choices": [],
      "default": "black",
      "description": "set foreground color (default \"black\")",
      "name": "fontcolor",
      "required": false,
      "typing": "Color"
    },
    {
      "alias": [
        "fontcolor_expr"
      ],
      "choices": [],
      "default": "",
      "description": "set foreground color expression (default \"\")",
      "name": "fontcolor_expr",
      "required": false,
      "typing": "String"
    },
    {
      "alias": [
        "boxcolor"
      ],
      "choices": [],
      "default": "white",
      "description": "set box color (default \"white\")",
      "name": "boxcolor",
      "required": false,
      "typing": "Color"
    },
    {
      "alias": [
        "bordercolor"
      ],
      "choices": [],
      "default": "black",
      "description": "set border color (default \"black\")",
      "name": "bordercolor",
      "required": false,
      "typing": "Color"
    },
    {
      "alias": [
        "shadowcolor"
      ],
      "choices": [],
      "default": "black",
      "description": "set shadow color (default \"black\")",
      "name": "shadowcolor",
      "required": false,
      "typing": "Color"
    },
    {
      "alias": [
        "box"
      ],
      "choices": [],
      "default": false,
      "description": "set box (default false)",
      "name": "box",
      "required": false,
      "typing": "Boolean"
    },
    {
      "alias": [
        "boxborderw"
      ],
      "choices": [],
      "default": "0",
      "description": "set box borders width (default \"0\")",
      "name": "boxborderw",
      "required": false,
      "typing": "String"
    },
    {
      "alias": [
        "line_spacing"
      ],
      "choices": [],
      "default": 0,
      "description": "set line spacing in pixels (from INT_MIN to INT_MAX) (default 0)",
      "name": "line_spacing",
      "required": false,
      "typing": "Int"
    },
    {
      "alias": [
        "fontsize"
      ],
      "choices": [],
      "default": null,
      "description": "set font size",
      "name": "fontsize",
      "required": false,
      "typing": "String"
    },
    {
      "alias": [
        "text_align"
      ],
      "choices": [
        {
          "help": "",
          "name": "left",
          "value": "left"
        },
        {
          "help": "",
          "name": "L",
          "value": "L"
        },
        {
          "help": "",
          "name": "right",
          "value": "right"
        },
        {
          "help": "",
          "name": "R",
          "value": "R"
        },
        {
          "help": "",
          "name": "center",
          "value": "center"
        },
        {
          "help": "",
          "name": "C",
          "value": "C"
        },
        {
          "help": "",
          "name": "top",
          "value": "top"
        },
        {
          "help": "",
          "name": "T",
          "value": "T"
        },
        {
          "help": "",
          "name": "bottom",
          "value": "bottom"
        },
        {
          "help": "",
          "name": "B",
          "value": "B"
        },
        {
          "help": "",
          "name": "middle",
          "value": "middle"
        },
        {
          "help": "",
          "name": "M",
          "value": "M"
        }
      ],
      "default": "0",
      "description": "set text alignment (default 0)",
      "name": "text_align",
      "required": false,
      "typing": "Flags"
    },
    {
      "alias": [
        "x"
      ],
      "choices": [],
      "default": "0",
      "description": "set x expression (default \"0\")",
      "name": "x",
      "required": false,
      "typing": "String"
    },
    {
      "alias": [
        "y"
      ],
      "choices": [],
      "default": "0",
      "description": "set y expression (default \"0\")",
      "name": "y",
      "required": false,
      "typing": "String"
    },
    {
      "alias": [
        "boxw"
      ],
      "choices": [],
      "default": 0,
      "description": "set box width (from 0 to INT_MAX) (default 0)",
      "name": "boxw",
      "required": false,
      "typing": "Int"
    },
    {
      "alias": [
        "boxh"
      ],
      "choices": [],
      "default": 0,
      "description": "set box height (from 0 to INT_MAX) (default 0)",
      "name": "boxh",
      "required": false,
      "typing": "Int"
    },
    {
      "alias": [
        "shadowx"
      ],
      "choices": [],
      "default": 0,
      "description": "set shadow x offset (from INT_MIN to INT_MAX) (default 0)",
      "name": "shadowx",
      "required": false,
      "typing": "Int"
    },
    {
      "alias": [
        "shadowy"
      ],
      "choices": [],
      "default": 0,
      "description": "set shadow y offset (from INT_MIN to INT_MAX) (default 0)",
      "name": "shadowy",
      "required": false,
      "typing": "Int"
    },
    {
      "alias": [
        "borderw"
      ],
      "choices": [],
      "default": 0,
      "description": "set border width (from INT_MIN to INT_MAX) (default 0)",
      "name": "borderw",
      "required": false,
      "typing": "Int"
    },
    {
      "alias": [
        "tabsize"
      ],
      "choices": [],
      "default": 4,
      "description": "set tab size (from 0 to INT_MAX) (default 4)",
      "name": "tabsize",
      "required": false,
      "typing": "Int"
    },
    {
      "alias": [
        "basetime"
      ],
      "choices": [],
      "default": "I64_MIN",
      "description": "set base time (from I64_MIN to I64_MAX) (default I64_MIN)",
      "name": "basetime",
      "required": false,
      "typing": "Int64"
    },
    {
      "alias": [
        "font"
      ],
      "choices": [],
      "default": "Sans",
      "description": "Font name (default \"Sans\")",
      "name": "font",
      "required": false,
      "typing": "String"
    },
    {
      "alias": [
        "expansion"
      ],
      "choices": [
        {
          "help": "set no expansion",
          "name": "none",
          "value": "0"
        },
        {
          "help": "set normal expansion",
          "name": "normal",
          "value": "1"
        },
        {
          "help": "set strftime expansion (deprecated)",
          "name": "strftime",
          "value": "2"
        }
      ],
      "default": "normal",
      "description": "set the expansion mode (from 0 to 2) (default normal)",
      "name": "expansion",
      "required": false,
      "typing": "Int"
    },
    {
      "alias": [
        "y_align"
      ],
      "choices": [
        {
          "help": "y is referred to the top of the first text line",
          "name": "text",
          "value": "0"
        },
        {
          "help": "y is referred to the baseline of the first line",
          "name": "baseline",
          "value": "1"
        },
        {
          "help": "y is referred to the font defined line metrics",
          "name": "font",
          "value": "2"
        }
      ],
      "default": "text",
      "description": "set the y alignment (from 0 to 2) (default text)",
      "name": "y_align",
      "required": false,
      "typing": "Int"
    },
    {
      "alias": [
        "timecode"
      ],
      "choices": [],
      "default": null,
      "description": "set initial timecode",
      "name": "timecode",
      "required": false,
      "typing": "String"
    },
    {
      "alias": [
        "tc24hmax"
      ],
      "choices": [],
      "default": false,
      "description": "set 24 hours max (timecode only) (default false)",
      "name": "tc24hmax",
      "required": false,
      "typing": "Boolean"
    },
    {
      "alias": [
        "timecode_rate",
        "r",
        "rate"
      ],
      "choices": [],
      "default": "0/1",
      "description": "set rate (timecode only) (from 0 to INT_MAX) (default 0/1)",
      "name": "timecode_rate",
      "required": false,
      "typing": "Rational"
    },
    {
      "alias": [
        "reload"
      ],
      "choices": [],
      "default": 0,
      "description": "reload text file at specified frame interval (from 0 to INT_MAX) (default 0)",
      "name": "reload",
      "required": false,
      "typing": "Int"
    },
    {
      "alias": [
        "alpha"
      ],
      "choices": [],
      "default": "1",
      "description": "apply alpha while rendering (default \"1\")",
      "name": "alpha",
      "required": false,
      "typing": "String"
    },
    {
      "alias": [
        "fix_bounds"
      ],
      "choices": [],
      "default": false,
      "description": "check and fix text coords to avoid clipping (default false)",
      "name": "fix_bounds",
      "required": false,
      "typing": "Boolean"
    },
    {
      "alias": [
        "start_number"
      ],
      "choices": [],
      "default": 0,
      "description": "start frame number for n/frame_num variable (from 0 to INT_MAX) (default 0)",
      "name": "start_number",
      "required": false,
      "typing": "Int"
    },
    {
      "alias": [
        "text_source"
      ],
      "choices": [],
      "default": null,
      "description": "the source of text",
      "name": "text_source",
      "required": false,
      "typing": "String"
    },
    {
      "alias": [
        "ft_load_flags"
      ],
      "choices": [
        {
          "help": "",
          "name": "default",
          "value": "default"
        },
        {
          "help": "",
          "name": "no_scale",
          "value": "no_scale"
        },
        {
          "help": "",
          "name": "no_hinting",
          "value": "no_hinting"
        },
        {
          "help": "",
          "name": "render",
          "value": "render"
        },
        {
          "help": "",
          "name": "no_bitmap",
          "value": "no_bitmap"
        },
        {
          "help": "",
          "name": "vertical_layout",
          "value": "vertical_layout"
        },
        {
          "help": "",
          "name": "force_autohint",
          "value": "force_autohint"
        },
        {
          "help": "",
          "name": "crop_bitmap",
          "value": "crop_bitmap"
        },
        {
          "help": "",
          "name": "pedantic",
          "value": "pedantic"
        },
        {
          "help": "",
          "name": "ignore_global_advance_width",
          "value": "ignore_global_advance_width"
        },
        {
          "help": "",
          "name": "no_recurse",
          "value": "no_recurse"
        },
        {
          "help": "",
          "name": "ignore_transform",
          "value": "ignore_transform"
        },
        {
          "help": "",
          "name": "monochrome",
          "value": "monochrome"
        },
        {
          "help": "",
          "name": "linear_design",
          "value": "linear_design"
        },
        {
          "help": "",
          "name": "no_autohint",
          "value": "no_autohint"
        }
      ],
      "default": "0",
      "description": "set font loading flags for libfreetype (default 0)",
      "name": "ft_load_flags",
      "required": false,
      "typing": "Flags"
    },
    {
      "alias": [],
      "choices": [],
      "default": null,
      "description": "timeline editing",
      "name": "enable",
      "required": false,
      "typing": "str"
    }
  ],
  "output_stream_typings": [
    {
      "name": "default",
      "type": "video"
    }
  ],
  "ref": "https://ffmpeg.org/ffmpeg-filters.html#drawtext"
}
