{
  "description": "Buffer video frames, and make them available to the end of the filter graph.",
  "filter_type": "vsink",
  "formula_input_typings": null,
  "formula_output_typings": null,
  "id": "ff_vsink_buffer",
  "input_stream_typings": [
    {
      "name": "default",
      "type": "AVMEDIA_TYPE_VIDEO"
    }
  ],
  "is_input_dynamic": false,
  "is_output_dynamic": false,
  "is_support_framesync": false,
  "is_support_timeline": false,
  "name": "buffersink",
  "options": [
    {
      "alias": [
        "pix_fmts"
      ],
      "choices": [],
      "default": null,
      "description": "set the supported pixel formats",
      "name": "pix_fmts",
      "required": false,
      "typing": "str"
    }
  ],
  "output_stream_typings": [],
  "ref": "https://ffmpeg.org/ffmpeg-filters.html#buffersink"
}
